{
  "meteorite_landings": [
    {
      "name": "Gerald",
      "id": "10001",
      "recclass": "H4",
      "mass (g)": "5754",
      "reclat": "-75.6691",
      "reclong": "60.6936",
      "GeoLocation": "(-75.6691, 60.6936)"
    },
    {
      "name": "Dominique",
      "id": "10002",
      "recclass": "L6",
      "mass (g)": "1701",
      "reclat": "-9.4378",
      "reclong": "49.5751",
      "GeoLocation": "(-9.4378, 49.5751)"
    },
    {
      "name": "Malinda",
      "id": "10003",
      "recclass": "CI1",
      "mass (g)": "3482",
      "reclat": "35.3692",
      "reclong": "61.4206",
      "GeoLocation": "(35.3692, 61.4206)"
    },
    {
      "name": "Mary",
      "id": "10004",
      "recclass": "L5",
      "mass (g)": "5339",
      "reclat": "71.2364",
      "reclong": "-21.9294",
      "GeoLocation": "(71.2364, -21.9294)"
    },
    {
      "name": "Paula",
      "id": "10005",
      "recclass": "LL3-6",
      "mass (g)": "3920",
      "reclat": "64.3430",
      "reclong": "-52.1797",
      "GeoLocation": "(64.3430, -52.1797)"
    },
    {
      "name": "Marshall",
      "id": "10006",
      "recclass": "LL5",
      "mass (g)": "8562",
      "reclat": "-23.2369",
      "reclong": "38.1958",
      "GeoLocation": "(-23.2369, 38.1958)"
    },
    {
      "name": "Chu",
      "id": "10007",
      "recclass": "CV3",
      "mass (g)": "2335",
      "reclat": "-17.3402",
      "reclong": "-67.8611",
      "GeoLocation": "(-17.3402, -67.8611)"
    },
    {
      "name": "Ray",
      "id": "10008",
      "recclass": "H4",
      "mass (g)": "3559",
      "reclat": "-6.0383",
      "reclong": "-88.1275",
      "GeoLocation": "(-6.0383, -88.1275)"
    },
    {
      "name": "Josephine",
      "id": "10009",
      "recclass": "CR2-an",
      "mass (g)": "5698",
      "reclat": "16.0546",
      "reclong": "-32.5038",
      "GeoLocation": "(16.0546, -32.5038)"
    },
    {
      "name": "Helga",
      "id": "10010",
      "recclass": "L5",
      "mass (g)": "3644",
      "reclat": "74.4431",
      "reclong": "-65.2342",
      "GeoLocation": "(74.4431, -65.2342)"
    },
    {
      "name": "Frederic",
      "id": "10011",
      "recclass": "LL5",
      "mass (g)": "8987",
      "reclat": "75.8622",
      "reclong": "-80.7048",
      "GeoLocation": "(75.8622, -80.7048)"
    },
    {
      "name": "Kimberly",
      "id": "10012",
      "recclass": "LL5",
      "mass (g)": "8664",
      "reclat": "72.5899",
      "reclong": "-55.9818",
      "GeoLocation": "(72.5899, -55.9818)"
    },
    {
      "name": "Sharon",
      "id": "10013",
      "recclass": "H6",
      "mass (g)": "8813",
      "reclat": "-23.1671",
      "reclong": "-29.0407",
      "GeoLocation": "(-23.1671, -29.0407)"
    },
    {
      "name": "Laurel",
      "id": "10014",
      "recclass": "CV3",
      "mass (g)": "582",
      "reclat": "3.2310",
      "reclong": "-70.7159",
      "GeoLocation": "(3.2310, -70.7159)"
    },
    {
      "name": "Dustin",
      "id": "10015",
      "recclass": "CV3",
      "mass (g)": "4162",
      "reclat": "-51.1762",
      "reclong": "16.0275",
      "GeoLocation": "(-51.1762, 16.0275)"
    },
    {
      "name": "Cynthia",
      "id": "10016",
      "recclass": "CV3",
      "mass (g)": "3634",
      "reclat": "60.6188",
      "reclong": "-81.9882",
      "GeoLocation": "(60.6188, -81.9882)"
    },
    {
      "name": "Charles",
      "id": "10017",
      "recclass": "LL5",
      "mass (g)": "8094",
      "reclat": "-23.4236",
      "reclong": "-35.7212",
      "GeoLocation": "(-23.4236, -35.7212)"
    },
    {
      "name": "Jennifer",
      "id": "10018",
      "recclass": "CI1",
      "mass (g)": "6198",
      "reclat": "52.2286",
      "reclong": "24.8063",
      "GeoLocation": "(52.2286, 24.8063)"
    },
    {
      "name": "Nicholas",
      "id": "10019",
      "recclass": "L5",
      "mass (g)": "1917",
      "reclat": "-21.7673",
      "reclong": "42.0877",
      "GeoLocation": "(-21.7673, 42.0877)"
    },
    {
      "name": "Adriana",
      "id": "10020",
      "recclass": "CV3",
      "mass (g)": "4970",
      "reclat": "2.6816",
      "reclong": "45.6691",
      "GeoLocation": "(2.6816, 45.6691)"
    },
    {
      "name": "Lucia",
      "id": "10021",
      "recclass": "LL3-6",
      "mass (g)": "5362",
      "reclat": "52.7120",
      "reclong": "-69.5953",
      "GeoLocation": "(52.7120, -69.5953)"
    },
    {
      "name": "David",
      "id": "10022",
      "recclass": "CR2-an",
      "mass (g)": "4820",
      "reclat": "85.7144",
      "reclong": "39.0004",
      "GeoLocation": "(85.7144, 39.0004)"
    },
    {
      "name": "Brad",
      "id": "10023",
      "recclass": "L5",
      "mass (g)": "2605",
      "reclat": "-52.9484",
      "reclong": "41.9015",
      "GeoLocation": "(-52.9484, 41.9015)"
    },
    {
      "name": "Mark",
      "id": "10024",
      "recclass": "CI1",
      "mass (g)": "1272",
      "reclat": "-75.1423",
      "reclong": "42.5728",
      "GeoLocation": "(-75.1423, 42.5728)"
    },
    {
      "name": "Craig",
      "id": "10025",
      "recclass": "L6",
      "mass (g)": "6625",
      "reclat": "29.9307",
      "reclong": "-26.5546",
      "GeoLocation": "(29.9307, -26.5546)"
    },
    {
      "name": "Matthew",
      "id": "10026",
      "recclass": "EH4",
      "mass (g)": "9281",
      "reclat": "-7.2688",
      "reclong": "-85.9196",
      "GeoLocation": "(-7.2688, -85.9196)"
    },
    {
      "name": "Earl",
      "id": "10027",
      "recclass": "L5",
      "mass (g)": "7595",
      "reclat": "15.8100",
      "reclong": "-81.8848",
      "GeoLocation": "(15.8100, -81.8848)"
    },
    {
      "name": "Marvin",
      "id": "10028",
      "recclass": "LL3-6",
      "mass (g)": "313",
      "reclat": "-24.1677",
      "reclong": "5.5912",
      "GeoLocation": "(-24.1677, 5.5912)"
    },
    {
      "name": "Barry",
      "id": "10029",
      "recclass": "LL3-6",
      "mass (g)": "7492",
      "reclat": "24.0732",
      "reclong": "33.4294",
      "GeoLocation": "(24.0732, 33.4294)"
    },
    {
      "name": "Ana",
      "id": "10030",
      "recclass": "L5",
      "mass (g)": "7102",
      "reclat": "-17.0582",
      "reclong": "-25.8608",
      "GeoLocation": "(-17.0582, -25.8608)"
    },
    {
      "name": "Antonio",
      "id": "10031",
      "recclass": "LL5",
      "mass (g)": "6729",
      "reclat": "-66.2285",
      "reclong": "-41.1614",
      "GeoLocation": "(-66.2285, -41.1614)"
    },
    {
      "name": "Mary",
      "id": "10032",
      "recclass": "LL3-6",
      "mass (g)": "8838",
      "reclat": "3.8690",
      "reclong": "-50.9037",
      "GeoLocation": "(3.8690, -50.9037)"
    },
    {
      "name": "Paul",
      "id": "10033",
      "recclass": "LL3-6",
      "mass (g)": "1342",
      "reclat": "31.7209",
      "reclong": "7.9366",
      "GeoLocation": "(31.7209, 7.9366)"
    },
    {
      "name": "Mary",
      "id": "10034",
      "recclass": "H6",
      "mass (g)": "4227",
      "reclat": "68.6125",
      "reclong": "89.6593",
      "GeoLocation": "(68.6125, 89.6593)"
    },
    {
      "name": "Felipe",
      "id": "10035",
      "recclass": "H5",
      "mass (g)": "3983",
      "reclat": "28.0289",
      "reclong": "-50.3903",
      "GeoLocation": "(28.0289, -50.3903)"
    },
    {
      "name": "Ann",
      "id": "10036",
      "recclass": "CR2-an",
      "mass (g)": "61",
      "reclat": "-42.1717",
      "reclong": "-61.3470",
      "GeoLocation": "(-42.1717, -61.3470)"
    },
    {
      "name": "Tommy",
      "id": "10037",
      "recclass": "CI1",
      "mass (g)": "6846",
      "reclat": "24.0811",
      "reclong": "-39.3126",
      "GeoLocation": "(24.0811, -39.3126)"
    },
    {
      "name": "Marcus",
      "id": "10038",
      "recclass": "CI1",
      "mass (g)": "2918",
      "reclat": "64.6581",
      "reclong": "-27.6696",
      "GeoLocation": "(64.6581, -27.6696)"
    },
    {
      "name": "Alex",
      "id": "10039",
      "recclass": "H6",
      "mass (g)": "3808",
      "reclat": "14.9904",
      "reclong": "89.4559",
      "GeoLocation": "(14.9904, 89.4559)"
    },
    {
      "name": "Samuel",
      "id": "10040",
      "recclass": "CR2-an",
      "mass (g)": "7893",
      "reclat": "49.9545",
      "reclong": "34.1926",
      "GeoLocation": "(49.9545, 34.1926)"
    },
    {
      "name": "Leah",
      "id": "10041",
      "recclass": "CR2-an",
      "mass (g)": "6329",
      "reclat": "37.2002",
      "reclong": "81.8961",
      "GeoLocation": "(37.2002, 81.8961)"
    },
    {
      "name": "Philip",
      "id": "10042",
      "recclass": "H4",
      "mass (g)": "2929",
      "reclat": "78.5015",
      "reclong": "-57.3911",
      "GeoLocation": "(78.5015, -57.3911)"
    },
    {
      "name": "Carolyn",
      "id": "10043",
      "recclass": "CR2-an",
      "mass (g)": "9051",
      "reclat": "39.6407",
      "reclong": "22.9840",
      "GeoLocation": "(39.6407, 22.9840)"
    },
    {
      "name": "Darrell",
      "id": "10044",
      "recclass": "H4",
      "mass (g)": "7293",
      "reclat": "71.4609",
      "reclong": "-8.3718",
      "GeoLocation": "(71.4609, -8.3718)"
    },
    {
      "name": "Shanel",
      "id": "10045",
      "recclass": "CV3",
      "mass (g)": "6497",
      "reclat": "0.6412",
      "reclong": "-56.4161",
      "GeoLocation": "(0.6412, -56.4161)"
    },
    {
      "name": "Benjamin",
      "id": "10046",
      "recclass": "CV3",
      "mass (g)": "9493",
      "reclat": "43.9066",
      "reclong": "-28.6122",
      "GeoLocation": "(43.9066, -28.6122)"
    },
    {
      "name": "Patricia",
      "id": "10047",
      "recclass": "EH4",
      "mass (g)": "7651",
      "reclat": "-58.6866",
      "reclong": "-52.9993",
      "GeoLocation": "(-58.6866, -52.9993)"
    },
    {
      "name": "Teresa",
      "id": "10048",
      "recclass": "LL3-6",
      "mass (g)": "6934",
      "reclat": "17.5173",
      "reclong": "82.6029",
      "GeoLocation": "(17.5173, 82.6029)"
    },
    {
      "name": "Maurice",
      "id": "10049",
      "recclass": "H4",
      "mass (g)": "3314",
      "reclat": "-73.7922",
      "reclong": "41.9993",
      "GeoLocation": "(-73.7922, 41.9993)"
    },
    {
      "name": "Theresa",
      "id": "10050",
      "recclass": "H5",
      "mass (g)": "9428",
      "reclat": "-73.4886",
      "reclong": "70.4365",
      "GeoLocation": "(-73.4886, 70.4365)"
    },
    {
      "name": "Hector",
      "id": "10051",
      "recclass": "H5",
      "mass (g)": "7165",
      "reclat": "-72.5186",
      "reclong": "-73.1263",
      "GeoLocation": "(-72.5186, -73.1263)"
    },
    {
      "name": "David",
      "id": "10052",
      "recclass": "CR2-an",
      "mass (g)": "7837",
      "reclat": "17.7592",
      "reclong": "-37.8045",
      "GeoLocation": "(17.7592, -37.8045)"
    },
    {
      "name": "Randy",
      "id": "10053",
      "recclass": "LL5",
      "mass (g)": "4957",
      "reclat": "-37.9333",
      "reclong": "53.0132",
      "GeoLocation": "(-37.9333, 53.0132)"
    },
    {
      "name": "Jenifer",
      "id": "10054",
      "recclass": "H4",
      "mass (g)": "7106",
      "reclat": "25.1646",
      "reclong": "62.5936",
      "GeoLocation": "(25.1646, 62.5936)"
    },
    {
      "name": "Benjamin",
      "id": "10055",
      "recclass": "CI1",
      "mass (g)": "5841",
      "reclat": "-35.8842",
      "reclong": "37.3757",
      "GeoLocation": "(-35.8842, 37.3757)"
    },
    {
      "name": "Juliette",
      "id": "10056",
      "recclass": "L6",
      "mass (g)": "5789",
      "reclat": "-54.9099",
      "reclong": "10.2179",
      "GeoLocation": "(-54.9099, 10.2179)"
    },
    {
      "name": "Timothy",
      "id": "10057",
      "recclass": "CV3",
      "mass (g)": "3511",
      "reclat": "33.1755",
      "reclong": "-66.3481",
      "GeoLocation": "(33.1755, -66.3481)"
    },
    {
      "name": "Lynn",
      "id": "10058",
      "recclass": "L6",
      "mass (g)": "2060",
      "reclat": "19.5654",
      "reclong": "74.9029",
      "GeoLocation": "(19.5654, 74.9029)"
    },
    {
      "name": "Angela",
      "id": "10059",
      "recclass": "LL5",
      "mass (g)": "2050",
      "reclat": "63.7090",
      "reclong": "-31.3027",
      "GeoLocation": "(63.7090, -31.3027)"
    },
    {
      "name": "Wilson",
      "id": "10060",
      "recclass": "H4",
      "mass (g)": "3481",
      "reclat": "32.9985",
      "reclong": "11.6324",
      "GeoLocation": "(32.9985, 11.6324)"
    },
    {
      "name": "Marguerite",
      "id": "10061",
      "recclass": "H6",
      "mass (g)": "9523",
      "reclat": "32.0896",
      "reclong": "-67.8009",
      "GeoLocation": "(32.0896, -67.8009)"
    },
    {
      "name": "William",
      "id": "10062",
      "recclass": "L6",
      "mass (g)": "8046",
      "reclat": "-7.5330",
      "reclong": "-83.8840",
      "GeoLocation": "(-7.5330, -83.8840)"
    },
    {
      "name": "Derrick",
      "id": "10063",
      "recclass": "LL5",
      "mass (g)": "6971",
      "reclat": "-53.3368",
      "reclong": "-40.4965",
      "GeoLocation": "(-53.3368, -40.4965)"
    },
    {
      "name": "Hilma",
      "id": "10064",
      "recclass": "H4",
      "mass (g)": "4605",
      "reclat": "-86.2178",
      "reclong": "12.3718",
      "GeoLocation": "(-86.2178, 12.3718)"
    },
    {
      "name": "Brandon",
      "id": "10065",
      "recclass": "EH4",
      "mass (g)": "3455",
      "reclat": "82.0937",
      "reclong": "-72.6085",
      "GeoLocation": "(82.0937, -72.6085)"
    },
    {
      "name": "Arthur",
      "id": "10066",
      "recclass": "CI1",
      "mass (g)": "7233",
      "reclat": "-77.8768",
      "reclong": "81.5604",
      "GeoLocation": "(-77.8768, 81.5604)"
    },
    {
      "name": "Thomas",
      "id": "10067",
      "recclass": "CV3",
      "mass (g)": "7189",
      "reclat": "-1.3595",
      "reclong": "-89.8772",
      "GeoLocation": "(-1.3595, -89.8772)"
    },
    {
      "name": "Dorothy",
      "id": "10068",
      "recclass": "EH4",
      "mass (g)": "9144",
      "reclat": "75.5558",
      "reclong": "75.6130",
      "GeoLocation": "(75.5558, 75.6130)"
    },
    {
      "name": "Anna",
      "id": "10069",
      "recclass": "LL5",
      "mass (g)": "8473",
      "reclat": "59.0980",
      "reclong": "-7.3317",
      "GeoLocation": "(59.0980, -7.3317)"
    },
    {
      "name": "Mary",
      "id": "10070",
      "recclass": "CR2-an",
      "mass (g)": "6835",
      "reclat": "-70.8930",
      "reclong": "5.6662",
      "GeoLocation": "(-70.8930, 5.6662)"
    },
    {
      "name": "Margaret",
      "id": "10071",
      "recclass": "L6",
      "mass (g)": "4626",
      "reclat": "60.4478",
      "reclong": "46.6545",
      "GeoLocation": "(60.4478, 46.6545)"
    },
    {
      "name": "Paula",
      "id": "10072",
      "recclass": "CI1",
      "mass (g)": "7570",
      "reclat": "54.9934",
      "reclong": "3.5058",
      "GeoLocation": "(54.9934, 3.5058)"
    },
    {
      "name": "Melvin",
      "id": "10073",
      "recclass": "CI1",
      "mass (g)": "1087",
      "reclat": "-81.8546",
      "reclong": "58.0687",
      "GeoLocation": "(-81.8546, 58.0687)"
    },
    {
      "name": "John",
      "id": "10074",
      "recclass": "H5",
      "mass (g)": "3616",
      "reclat": "51.4388",
      "reclong": "-29.7264",
      "GeoLocation": "(51.4388, -29.7264)"
    },
    {
      "name": "Patricia",
      "id": "10075",
      "recclass": "LL5",
      "mass (g)": "7532",
      "reclat": "26.8378",
      "reclong": "40.8804",
      "GeoLocation": "(26.8378, 40.8804)"
    },
    {
      "name": "Steven",
      "id": "10076",
      "recclass": "EH4",
      "mass (g)": "2311",
      "reclat": "-32.1216",
      "reclong": "59.2255",
      "GeoLocation": "(-32.1216, 59.2255)"
    },
    {
      "name": "John",
      "id": "10077",
      "recclass": "LL3-6",
      "mass (g)": "8688",
      "reclat": "89.3689",
      "reclong": "-4.9507",
      "GeoLocation": "(89.3689, -4.9507)"
    },
    {
      "name": "Willodean",
      "id": "10078",
      "recclass": "L5",
      "mass (g)": "7218",
      "reclat": "-71.8830",
      "reclong": "-19.5791",
      "GeoLocation": "(-71.8830, -19.5791)"
    },
    {
      "name": "Lorraine",
      "id": "10079",
      "recclass": "LL5",
      "mass (g)": "2863",
      "reclat": "30.0871",
      "reclong": "3.9794",
      "GeoLocation": "(30.0871, 3.9794)"
    },
    {
      "name": "Charles",
      "id": "10080",
      "recclass": "H4",
      "mass (g)": "3601",
      "reclat": "-1.9309",
      "reclong": "-42.9204",
      "GeoLocation": "(-1.9309, -42.9204)"
    },
    {
      "name": "Martha",
      "id": "10081",
      "recclass": "CR2-an",
      "mass (g)": "2022",
      "reclat": "-64.5155",
      "reclong": "-81.3255",
      "GeoLocation": "(-64.5155, -81.3255)"
    },
    {
      "name": "Phylis",
      "id": "10082",
      "recclass": "L6",
      "mass (g)": "9028",
      "reclat": "-73.3747",
      "reclong": "32.1600",
      "GeoLocation": "(-73.3747, 32.1600)"
    },
    {
      "name": "Linda",
      "id": "10083",
      "recclass": "LL5",
      "mass (g)": "7106",
      "reclat": "56.8741",
      "reclong": "1.6650",
      "GeoLocation": "(56.8741, 1.6650)"
    },
    {
      "name": "Carolyn",
      "id": "10084",
      "recclass": "LL5",
      "mass (g)": "8332",
      "reclat": "-67.6518",
      "reclong": "-74.8028",
      "GeoLocation": "(-67.6518, -74.8028)"
    },
    {
      "name": "James",
      "id": "10085",
      "recclass": "H5",
      "mass (g)": "3548",
      "reclat": "-41.9669",
      "reclong": "16.1404",
      "GeoLocation": "(-41.9669, 16.1404)"
    },
    {
      "name": "Kara",
      "id": "10086",
      "recclass": "CR2-an",
      "mass (g)": "7932",
      "reclat": "36.0384",
      "reclong": "-84.6473",
      "GeoLocation": "(36.0384, -84.6473)"
    },
    {
      "name": "Rosa",
      "id": "10087",
      "recclass": "EH4",
      "mass (g)": "1649",
      "reclat": "47.5531",
      "reclong": "-28.0797",
      "GeoLocation": "(47.5531, -28.0797)"
    },
    {
      "name": "Terrence",
      "id": "10088",
      "recclass": "CV3",
      "mass (g)": "9106",
      "reclat": "24.8247",
      "reclong": "-25.4088",
      "GeoLocation": "(24.8247, -25.4088)"
    },
    {
      "name": "Stephanie",
      "id": "10089",
      "recclass": "H5",
      "mass (g)": "3608",
      "reclat": "-77.6103",
      "reclong": "75.0265",
      "GeoLocation": "(-77.6103, 75.0265)"
    },
    {
      "name": "Erica",
      "id": "10090",
      "recclass": "CV3",
      "mass (g)": "8427",
      "reclat": "-52.3101",
      "reclong": "-19.7219",
      "GeoLocation": "(-52.3101, -19.7219)"
    },
    {
      "name": "Cheryl",
      "id": "10091",
      "recclass": "CR2-an",
      "mass (g)": "6297",
      "reclat": "65.7173",
      "reclong": "55.1052",
      "GeoLocation": "(65.7173, 55.1052)"
    },
    {
      "name": "Jerry",
      "id": "10092",
      "recclass": "EH4",
      "mass (g)": "7990",
      "reclat": "8.6873",
      "reclong": "4.0909",
      "GeoLocation": "(8.6873, 4.0909)"
    },
    {
      "name": "Jaime",
      "id": "10093",
      "recclass": "LL3-6",
      "mass (g)": "8251",
      "reclat": "-2.5759",
      "reclong": "70.1828",
      "GeoLocation": "(-2.5759, 70.1828)"
    },
    {
      "name": "Mara",
      "id": "10094",
      "recclass": "CR2-an",
      "mass (g)": "2648",
      "reclat": "-79.1773",
      "reclong": "36.8169",
      "GeoLocation": "(-79.1773, 36.8169)"
    },
    {
      "name": "Frank",
      "id": "10095",
      "recclass": "CI1",
      "mass (g)": "9391",
      "reclat": "-29.0123",
      "reclong": "79.7602",
      "GeoLocation": "(-29.0123, 79.7602)"
    },
    {
      "name": "Karlene",
      "id": "10096",
      "recclass": "LL3-6",
      "mass (g)": "938",
      "reclat": "47.1647",
      "reclong": "78.9852",
      "GeoLocation": "(47.1647, 78.9852)"
    },
    {
      "name": "Daniel",
      "id": "10097",
      "recclass": "L5",
      "mass (g)": "4685",
      "reclat": "44.9992",
      "reclong": "17.5728",
      "GeoLocation": "(44.9992, 17.5728)"
    },
    {
      "name": "Richard",
      "id": "10098",
      "recclass": "LL5",
      "mass (g)": "936",
      "reclat": "6.8212",
      "reclong": "23.4244",
      "GeoLocation": "(6.8212, 23.4244)"
    },
    {
      "name": "John",
      "id": "10099",
      "recclass": "H6",
      "mass (g)": "7317",
      "reclat": "-46.4123",
      "reclong": "58.0161",
      "GeoLocation": "(-46.4123, 58.0161)"
    },
    {
      "name": "Warren",
      "id": "10100",
      "recclass": "H4",
      "mass (g)": "5089",
      "reclat": "76.0439",
      "reclong": "-50.8195",
      "GeoLocation": "(76.0439, -50.8195)"
    },
    {
      "name": "Nancy",
      "id": "10101",
      "recclass": "LL5",
      "mass (g)": "7573",
      "reclat": "-24.2027",
      "reclong": "-45.5237",
      "GeoLocation": "(-24.2027, -45.5237)"
    },
    {
      "name": "Allison",
      "id": "10102",
      "recclass": "LL5",
      "mass (g)": "9257",
      "reclat": "49.0342",
      "reclong": "-38.5766",
      "GeoLocation": "(49.0342, -38.5766)"
    },
    {
      "name": "Jessie",
      "id": "10103",
      "recclass": "H5",
      "mass (g)": "3592",
      "reclat": "88.8811",
      "reclong": "-84.3286",
      "GeoLocation": "(88.8811, -84.3286)"
    },
    {
      "name": "Kimberly",
      "id": "10104",
      "recclass": "LL5",
      "mass (g)": "3529",
      "reclat": "-62.1280",
      "reclong": "-52.3156",
      "GeoLocation": "(-62.1280, -52.3156)"
    },
    {
      "name": "Hazel",
      "id": "10105",
      "recclass": "LL5",
      "mass (g)": "5254",
      "reclat": "-70.4109",
      "reclong": "-83.0497",
      "GeoLocation": "(-70.4109, -83.0497)"
    },
    {
      "name": "Richard",
      "id": "10106",
      "recclass": "LL3-6",
      "mass (g)": "2036",
      "reclat": "17.3159",
      "reclong": "-1.2300",
      "GeoLocation": "(17.3159, -1.2300)"
    },
    {
      "name": "Michael",
      "id": "10107",
      "recclass": "L6",
      "mass (g)": "4796",
      "reclat": "-74.5748",
      "reclong": "72.9486",
      "GeoLocation": "(-74.5748, 72.9486)"
    },
    {
      "name": "George",
      "id": "10108",
      "recclass": "LL3-6",
      "mass (g)": "5147",
      "reclat": "59.6917",
      "reclong": "-54.2004",
      "GeoLocation": "(59.6917, -54.2004)"
    },
    {
      "name": "Jayson",
      "id": "10109",
      "recclass": "H5",
      "mass (g)": "5878",
      "reclat": "38.1872",
      "reclong": "54.6266",
      "GeoLocation": "(38.1872, 54.6266)"
    },
    {
      "name": "James",
      "id": "10110",
      "recclass": "EH4",
      "mass (g)": "6173",
      "reclat": "89.9512",
      "reclong": "-1.4196",
      "GeoLocation": "(89.9512, -1.4196)"
    },
    {
      "name": "Lisa",
      "id": "10111",
      "recclass": "H6",
      "mass (g)": "496",
      "reclat": "26.4043",
      "reclong": "-78.3046",
      "GeoLocation": "(26.4043, -78.3046)"
    },
    {
      "name": "Gary",
      "id": "10112",
      "recclass": "EH4",
      "mass (g)": "5705",
      "reclat": "-5.2903",
      "reclong": "79.2833",
      "GeoLocation": "(-5.2903, 79.2833)"
    },
    {
      "name": "Daisy",
      "id": "10113",
      "recclass": "CR2-an",
      "mass (g)": "8993",
      "reclat": "-3.4126",
      "reclong": "31.8077",
      "GeoLocation": "(-3.4126, 31.8077)"
    },
    {
      "name": "Hong",
      "id": "10114",
      "recclass": "CI1",
      "mass (g)": "5616",
      "reclat": "48.1929",
      "reclong": "25.7779",
      "GeoLocation": "(48.1929, 25.7779)"
    },
    {
      "name": "Amanda",
      "id": "10115",
      "recclass": "LL5",
      "mass (g)": "4606",
      "reclat": "-31.1824",
      "reclong": "-30.9219",
      "GeoLocation": "(-31.1824, -30.9219)"
    },
    {
      "name": "George",
      "id": "10116",
      "recclass": "CV3",
      "mass (g)": "2166",
      "reclat": "88.6021",
      "reclong": "-9.2386",
      "GeoLocation": "(88.6021, -9.2386)"
    },
    {
      "name": "Fermin",
      "id": "10117",
      "recclass": "H4",
      "mass (g)": "7797",
      "reclat": "-89.7739",
      "reclong": "-87.7155",
      "GeoLocation": "(-89.7739, -87.7155)"
    },
    {
      "name": "Brian",
      "id": "10118",
      "recclass": "LL3-6",
      "mass (g)": "341",
      "reclat": "69.8606",
      "reclong": "58.1163",
      "GeoLocation": "(69.8606, 58.1163)"
    },
    {
      "name": "Lisa",
      "id": "10119",
      "recclass": "H6",
      "mass (g)": "4723",
      "reclat": "-1.9933",
      "reclong": "50.5105",
      "GeoLocation": "(-1.9933, 50.5105)"
    },
    {
      "name": "Yoko",
      "id": "10120",
      "recclass": "H6",
      "mass (g)": "5850",
      "reclat": "10.0957",
      "reclong": "65.3333",
      "GeoLocation": "(10.0957, 65.3333)"
    },
    {
      "name": "Robert",
      "id": "10121",
      "recclass": "CR2-an",
      "mass (g)": "4181",
      "reclat": "-59.6050",
      "reclong": "-32.4962",
      "GeoLocation": "(-59.6050, -32.4962)"
    },
    {
      "name": "Sara",
      "id": "10122",
      "recclass": "LL3-6",
      "mass (g)": "5332",
      "reclat": "12.0046",
      "reclong": "23.4560",
      "GeoLocation": "(12.0046, 23.4560)"
    },
    {
      "name": "Tony",
      "id": "10123",
      "recclass": "LL3-6",
      "mass (g)": "658",
      "reclat": "7.1365",
      "reclong": "2.6438",
      "GeoLocation": "(7.1365, 2.6438)"
    },
    {
      "name": "Bobby",
      "id": "10124",
      "recclass": "L5",
      "mass (g)": "8793",
      "reclat": "-65.3196",
      "reclong": "24.3672",
      "GeoLocation": "(-65.3196, 24.3672)"
    },
    {
      "name": "John",
      "id": "10125",
      "recclass": "LL3-6",
      "mass (g)": "54",
      "reclat": "-3.1176",
      "reclong": "89.9895",
      "GeoLocation": "(-3.1176, 89.9895)"
    },
    {
      "name": "Connie",
      "id": "10126",
      "recclass": "L5",
      "mass (g)": "3891",
      "reclat": "31.2090",
      "reclong": "-84.6270",
      "GeoLocation": "(31.2090, -84.6270)"
    },
    {
      "name": "Jane",
      "id": "10127",
      "recclass": "CI1",
      "mass (g)": "8291",
      "reclat": "85.0465",
      "reclong": "15.6625",
      "GeoLocation": "(85.0465, 15.6625)"
    },
    {
      "name": "Brianne",
      "id": "10128",
      "recclass": "CR2-an",
      "mass (g)": "1767",
      "reclat": "-16.3033",
      "reclong": "-26.6412",
      "GeoLocation": "(-16.3033, -26.6412)"
    },
    {
      "name": "Elaine",
      "id": "10129",
      "recclass": "CR2-an",
      "mass (g)": "3361",
      "reclat": "-42.3794",
      "reclong": "-59.5781",
      "GeoLocation": "(-42.3794, -59.5781)"
    },
    {
      "name": "Michelle",
      "id": "10130",
      "recclass": "EH4",
      "mass (g)": "6400",
      "reclat": "-62.5246",
      "reclong": "-41.8869",
      "GeoLocation": "(-62.5246, -41.8869)"
    },
    {
      "name": "Wade",
      "id": "10131",
      "recclass": "LL5",
      "mass (g)": "7978",
      "reclat": "-7.3535",
      "reclong": "32.6906",
      "GeoLocation": "(-7.3535, 32.6906)"
    },
    {
      "name": "Beatrice",
      "id": "10132",
      "recclass": "H6",
      "mass (g)": "8336",
      "reclat": "-56.2123",
      "reclong": "35.8634",
      "GeoLocation": "(-56.2123, 35.8634)"
    },
    {
      "name": "Debbie",
      "id": "10133",
      "recclass": "CV3",
      "mass (g)": "5986",
      "reclat": "78.6403",
      "reclong": "-72.3828",
      "GeoLocation": "(78.6403, -72.3828)"
    },
    {
      "name": "Betty",
      "id": "10134",
      "recclass": "CR2-an",
      "mass (g)": "5403",
      "reclat": "-28.3060",
      "reclong": "32.9140",
      "GeoLocation": "(-28.3060, 32.9140)"
    },
    {
      "name": "Travis",
      "id": "10135",
      "recclass": "H6",
      "mass (g)": "3225",
      "reclat": "-9.5380",
      "reclong": "81.4390",
      "GeoLocation": "(-9.5380, 81.4390)"
    },
    {
      "name": "Frederick",
      "id": "10136",
      "recclass": "CV3",
      "mass (g)": "7642",
      "reclat": "-9.7728",
      "reclong": "55.9031",
      "GeoLocation": "(-9.7728, 55.9031)"
    },
    {
      "name": "Pete",
      "id": "10137",
      "recclass": "LL3-6",
      "mass (g)": "5952",
      "reclat": "-85.3419",
      "reclong": "-9.3165",
      "GeoLocation": "(-85.3419, -9.3165)"
    },
    {
      "name": "John",
      "id": "10138",
      "recclass": "CV3",
      "mass (g)": "8393",
      "reclat": "-56.6581",
      "reclong": "-47.9661",
      "GeoLocation": "(-56.6581, -47.9661)"
    },
    {
      "name": "Randy",
      "id": "10139",
      "recclass": "H6",
      "mass (g)": "1806",
      "reclat": "-16.3030",
      "reclong": "26.7125",
      "GeoLocation": "(-16.3030, 26.7125)"
    },
    {
      "name": "Earl",
      "id": "10140",
      "recclass": "CV3",
      "mass (g)": "8951",
      "reclat": "7.2636",
      "reclong": "65.0002",
      "GeoLocation": "(7.2636, 65.0002)"
    },
    {
      "name": "William",
      "id": "10141",
      "recclass": "LL5",
      "mass (g)": "2046",
      "reclat": "-34.4436",
      "reclong": "-65.4854",
      "GeoLocation": "(-34.4436, -65.4854)"
    },
    {
      "name": "Gregory",
      "id": "10142",
      "recclass": "H4",
      "mass (g)": "8872",
      "reclat": "37.7038",
      "reclong": "-64.6142",
      "GeoLocation": "(37.7038, -64.6142)"
    },
    {
      "name": "Ruth",
      "id": "10143",
      "recclass": "CR2-an",
      "mass (g)": "7579",
      "reclat": "-55.4492",
      "reclong": "-25.1360",
      "GeoLocation": "(-55.4492, -25.1360)"
    },
    {
      "name": "Paul",
      "id": "10144",
      "recclass": "L5",
      "mass (g)": "6331",
      "reclat": "-48.6976",
      "reclong": "65.5108",
      "GeoLocation": "(-48.6976, 65.5108)"
    },
    {
      "name": "John",
      "id": "10145",
      "recclass": "CV3",
      "mass (g)": "1207",
      "reclat": "60.6755",
      "reclong": "56.8235",
      "GeoLocation": "(60.6755, 56.8235)"
    },
    {
      "name": "Zachary",
      "id": "10146",
      "recclass": "EH4",
      "mass (g)": "6229",
      "reclat": "-86.2927",
      "reclong": "53.9592",
      "GeoLocation": "(-86.2927, 53.9592)"
    },
    {
      "name": "Fredric",
      "id": "10147",
      "recclass": "CR2-an",
      "mass (g)": "2267",
      "reclat": "-85.6239",
      "reclong": "61.4570",
      "GeoLocation": "(-85.6239, 61.4570)"
    },
    {
      "name": "Ann",
      "id": "10148",
      "recclass": "CI1",
      "mass (g)": "1903",
      "reclat": "87.3733",
      "reclong": "47.0914",
      "GeoLocation": "(87.3733, 47.0914)"
    },
    {
      "name": "Linda",
      "id": "10149",
      "recclass": "CV3",
      "mass (g)": "1602",
      "reclat": "5.7798",
      "reclong": "84.0263",
      "GeoLocation": "(5.7798, 84.0263)"
    },
    {
      "name": "Paula",
      "id": "10150",
      "recclass": "L6",
      "mass (g)": "581",
      "reclat": "-54.3204",
      "reclong": "79.8243",
      "GeoLocation": "(-54.3204, 79.8243)"
    },
    {
      "name": "Michael",
      "id": "10151",
      "recclass": "H5",
      "mass (g)": "544",
      "reclat": "-19.7669",
      "reclong": "70.4801",
      "GeoLocation": "(-19.7669, 70.4801)"
    },
    {
      "name": "Susan",
      "id": "10152",
      "recclass": "L5",
      "mass (g)": "9853",
      "reclat": "28.2274",
      "reclong": "-12.9948",
      "GeoLocation": "(28.2274, -12.9948)"
    },
    {
      "name": "Nina",
      "id": "10153",
      "recclass": "LL3-6",
      "mass (g)": "1868",
      "reclat": "34.6497",
      "reclong": "-72.5948",
      "GeoLocation": "(34.6497, -72.5948)"
    },
    {
      "name": "Mark",
      "id": "10154",
      "recclass": "L6",
      "mass (g)": "8949",
      "reclat": "-19.2861",
      "reclong": "-35.2554",
      "GeoLocation": "(-19.2861, -35.2554)"
    },
    {
      "name": "Francisca",
      "id": "10155",
      "recclass": "L5",
      "mass (g)": "4917",
      "reclat": "68.2681",
      "reclong": "-7.6371",
      "GeoLocation": "(68.2681, -7.6371)"
    },
    {
      "name": "Mary",
      "id": "10156",
      "recclass": "CI1",
      "mass (g)": "6201",
      "reclat": "-33.4372",
      "reclong": "27.3302",
      "GeoLocation": "(-33.4372, 27.3302)"
    },
    {
      "name": "Shannon",
      "id": "10157",
      "recclass": "CR2-an",
      "mass (g)": "7587",
      "reclat": "-67.0981",
      "reclong": "-66.0576",
      "GeoLocation": "(-67.0981, -66.0576)"
    },
    {
      "name": "Edith",
      "id": "10158",
      "recclass": "EH4",
      "mass (g)": "9239",
      "reclat": "11.3539",
      "reclong": "24.9350",
      "GeoLocation": "(11.3539, 24.9350)"
    },
    {
      "name": "Jonathan",
      "id": "10159",
      "recclass": "CV3",
      "mass (g)": "324",
      "reclat": "-1.0186",
      "reclong": "-25.0427",
      "GeoLocation": "(-1.0186, -25.0427)"
    },
    {
      "name": "Tyrone",
      "id": "10160",
      "recclass": "H5",
      "mass (g)": "3018",
      "reclat": "12.5070",
      "reclong": "-57.3540",
      "GeoLocation": "(12.5070, -57.3540)"
    },
    {
      "name": "Jeff",
      "id": "10161",
      "recclass": "LL3-6",
      "mass (g)": "623",
      "reclat": "-55.1970",
      "reclong": "86.0018",
      "GeoLocation": "(-55.1970, 86.0018)"
    },
    {
      "name": "Richard",
      "id": "10162",
      "recclass": "L6",
      "mass (g)": "5215",
      "reclat": "22.0063",
      "reclong": "68.8072",
      "GeoLocation": "(22.0063, 68.8072)"
    },
    {
      "name": "Jennifer",
      "id": "10163",
      "recclass": "CI1",
      "mass (g)": "5644",
      "reclat": "23.1001",
      "reclong": "-68.0835",
      "GeoLocation": "(23.1001, -68.0835)"
    },
    {
      "name": "Carla",
      "id": "10164",
      "recclass": "LL3-6",
      "mass (g)": "1314",
      "reclat": "-88.8335",
      "reclong": "34.3459",
      "GeoLocation": "(-88.8335, 34.3459)"
    },
    {
      "name": "Manuel",
      "id": "10165",
      "recclass": "LL3-6",
      "mass (g)": "8821",
      "reclat": "-8.1810",
      "reclong": "-16.3926",
      "GeoLocation": "(-8.1810, -16.3926)"
    },
    {
      "name": "Don",
      "id": "10166",
      "recclass": "L5",
      "mass (g)": "7840",
      "reclat": "-49.8344",
      "reclong": "-64.6104",
      "GeoLocation": "(-49.8344, -64.6104)"
    },
    {
      "name": "John",
      "id": "10167",
      "recclass": "EH4",
      "mass (g)": "7937",
      "reclat": "30.2587",
      "reclong": "79.0040",
      "GeoLocation": "(30.2587, 79.0040)"
    },
    {
      "name": "Walter",
      "id": "10168",
      "recclass": "H5",
      "mass (g)": "9277",
      "reclat": "-69.1700",
      "reclong": "-43.5584",
      "GeoLocation": "(-69.1700, -43.5584)"
    },
    {
      "name": "Peter",
      "id": "10169",
      "recclass": "L5",
      "mass (g)": "3348",
      "reclat": "11.5093",
      "reclong": "-59.6834",
      "GeoLocation": "(11.5093, -59.6834)"
    },
    {
      "name": "Jessica",
      "id": "10170",
      "recclass": "CV3",
      "mass (g)": "5059",
      "reclat": "55.5763",
      "reclong": "-35.8523",
      "GeoLocation": "(55.5763, -35.8523)"
    },
    {
      "name": "Marisol",
      "id": "10171",
      "recclass": "CV3",
      "mass (g)": "7419",
      "reclat": "-12.9202",
      "reclong": "33.6740",
      "GeoLocation": "(-12.9202, 33.6740)"
    },
    {
      "name": "Walter",
      "id": "10172",
      "recclass": "H4",
      "mass (g)": "4115",
      "reclat": "60.4026",
      "reclong": "35.8682",
      "GeoLocation": "(60.4026, 35.8682)"
    },
    {
      "name": "Pamela",
      "id": "10173",
      "recclass": "H5",
      "mass (g)": "3939",
      "reclat": "-16.0065",
      "reclong": "42.0716",
      "GeoLocation": "(-16.0065, 42.0716)"
    },
    {
      "name": "Kathryn",
      "id": "10174",
      "recclass": "LL5",
      "mass (g)": "6505",
      "reclat": "-46.7744",
      "reclong": "15.9755",
      "GeoLocation": "(-46.7744, 15.9755)"
    },
    {
      "name": "Betty",
      "id": "10175",
      "recclass": "H6",
      "mass (g)": "9209",
      "reclat": "87.5806",
      "reclong": "-65.9309",
      "GeoLocation": "(87.5806, -65.9309)"
    },
    {
      "name": "Cornelius",
      "id": "10176",
      "recclass": "L5",
      "mass (g)": "5333",
      "reclat": "-58.9483",
      "reclong": "50.8735",
      "GeoLocation": "(-58.9483, 50.8735)"
    },
    {
      "name": "Edith",
      "id": "10177",
      "recclass": "H6",
      "mass (g)": "9579",
      "reclat": "66.1572",
      "reclong": "-31.2725",
      "GeoLocation": "(66.1572, -31.2725)"
    },
    {
      "name": "Margaret",
      "id": "10178",
      "recclass": "LL3-6",
      "mass (g)": "8847",
      "reclat": "29.9969",
      "reclong": "74.1068",
      "GeoLocation": "(29.9969, 74.1068)"
    },
    {
      "name": "Mike",
      "id": "10179",
      "recclass": "CI1",
      "mass (g)": "2954",
      "reclat": "49.7539",
      "reclong": "48.2788",
      "GeoLocation": "(49.7539, 48.2788)"
    },
    {
      "name": "Howard",
      "id": "10180",
      "recclass": "LL5",
      "mass (g)": "4773",
      "reclat": "46.7987",
      "reclong": "77.9990",
      "GeoLocation": "(46.7987, 77.9990)"
    },
    {
      "name": "Tamera",
      "id": "10181",
      "recclass": "CI1",
      "mass (g)": "9953",
      "reclat": "59.6237",
      "reclong": "58.5280",
      "GeoLocation": "(59.6237, 58.5280)"
    },
    {
      "name": "Wallace",
      "id": "10182",
      "recclass": "H6",
      "mass (g)": "9763",
      "reclat": "81.8072",
      "reclong": "14.7222",
      "GeoLocation": "(81.8072, 14.7222)"
    },
    {
      "name": "Vicky",
      "id": "10183",
      "recclass": "CI1",
      "mass (g)": "1028",
      "reclat": "-18.7040",
      "reclong": "15.0914",
      "GeoLocation": "(-18.7040, 15.0914)"
    },
    {
      "name": "Dolores",
      "id": "10184",
      "recclass": "LL3-6",
      "mass (g)": "9560",
      "reclat": "17.5336",
      "reclong": "0.7100",
      "GeoLocation": "(17.5336, 0.7100)"
    },
    {
      "name": "Debbie",
      "id": "10185",
      "recclass": "L6",
      "mass (g)": "6553",
      "reclat": "68.3090",
      "reclong": "53.1546",
      "GeoLocation": "(68.3090, 53.1546)"
    },
    {
      "name": "Lisa",
      "id": "10186",
      "recclass": "H5",
      "mass (g)": "1853",
      "reclat": "77.8868",
      "reclong": "81.0087",
      "GeoLocation": "(77.8868, 81.0087)"
    },
    {
      "name": "Phyllis",
      "id": "10187",
      "recclass": "L5",
      "mass (g)": "4337",
      "reclat": "-73.4925",
      "reclong": "12.4202",
      "GeoLocation": "(-73.4925, 12.4202)"
    },
    {
      "name": "Kenna",
      "id": "10188",
      "recclass": "CI1",
      "mass (g)": "2295",
      "reclat": "-4.7201",
      "reclong": "70.4833",
      "GeoLocation": "(-4.7201, 70.4833)"
    },
    {
      "name": "James",
      "id": "10189",
      "recclass": "L6",
      "mass (g)": "4281",
      "reclat": "-31.4457",
      "reclong": "-56.2754",
      "GeoLocation": "(-31.4457, -56.2754)"
    },
    {
      "name": "Patricia",
      "id": "10190",
      "recclass": "H5",
      "mass (g)": "2211",
      "reclat": "44.1535",
      "reclong": "-61.5404",
      "GeoLocation": "(44.1535, -61.5404)"
    },
    {
      "name": "Harry",
      "id": "10191",
      "recclass": "H5",
      "mass (g)": "4486",
      "reclat": "50.2254",
      "reclong": "2.3088",
      "GeoLocation": "(50.2254, 2.3088)"
    },
    {
      "name": "Bonnie",
      "id": "10192",
      "recclass": "CR2-an",
      "mass (g)": "1506",
      "reclat": "-31.8314",
      "reclong": "38.0977",
      "GeoLocation": "(-31.8314, 38.0977)"
    },
    {
      "name": "Ingrid",
      "id": "10193",
      "recclass": "H5",
      "mass (g)": "1081",
      "reclat": "46.9979",
      "reclong": "-1.5137",
      "GeoLocation": "(46.9979, -1.5137)"
    },
    {
      "name": "Cheryl",
      "id": "10194",
      "recclass": "L5",
      "mass (g)": "1771",
      "reclat": "-44.8430",
      "reclong": "40.9419",
      "GeoLocation": "(-44.8430, 40.9419)"
    },
    {
      "name": "William",
      "id": "10195",
      "recclass": "H5",
      "mass (g)": "882",
      "reclat": "-61.7878",
      "reclong": "-45.4911",
      "GeoLocation": "(-61.7878, -45.4911)"
    },
    {
      "name": "Shirley",
      "id": "10196",
      "recclass": "L5",
      "mass (g)": "488",
      "reclat": "-33.0125",
      "reclong": "-59.7343",
      "GeoLocation": "(-33.0125, -59.7343)"
    },
    {
      "name": "Charles",
      "id": "10197",
      "recclass": "H6",
      "mass (g)": "9944",
      "reclat": "-43.9616",
      "reclong": "0.4861",
      "GeoLocation": "(-43.9616, 0.4861)"
    },
    {
      "name": "Frederick",
      "id": "10198",
      "recclass": "LL5",
      "mass (g)": "8061",
      "reclat": "12.4565",
      "reclong": "-52.9708",
      "GeoLocation": "(12.4565, -52.9708)"
    },
    {
      "name": "Jennifer",
      "id": "10199",
      "recclass": "CI1",
      "mass (g)": "4085",
      "reclat": "-68.5891",
      "reclong": "-71.5851",
      "GeoLocation": "(-68.5891, -71.5851)"
    },
    {
      "name": "Michelle",
      "id": "10200",
      "recclass": "H4",
      "mass (g)": "1779",
      "reclat": "-89.7534",
      "reclong": "-64.8788",
      "GeoLocation": "(-89.7534, -64.8788)"
    },
    {
      "name": "Jayson",
      "id": "10201",
      "recclass": "H6",
      "mass (g)": "8389",
      "reclat": "-27.4848",
      "reclong": "-30.0230",
      "GeoLocation": "(-27.4848, -30.0230)"
    },
    {
      "name": "John",
      "id": "10202",
      "recclass": "LL5",
      "mass (g)": "9252",
      "reclat": "26.9714",
      "reclong": "34.3230",
      "GeoLocation": "(26.9714, 34.3230)"
    },
    {
      "name": "Annie",
      "id": "10203",
      "recclass": "CI1",
      "mass (g)": "1912",
      "reclat": "-35.0818",
      "reclong": "-42.5204",
      "GeoLocation": "(-35.0818, -42.5204)"
    },
    {
      "name": "Sherry",
      "id": "10204",
      "recclass": "EH4",
      "mass (g)": "9087",
      "reclat": "22.2240",
      "reclong": "-66.8200",
      "GeoLocation": "(22.2240, -66.8200)"
    },
    {
      "name": "Peter",
      "id": "10205",
      "recclass": "LL5",
      "mass (g)": "639",
      "reclat": "-24.0783",
      "reclong": "-72.5997",
      "GeoLocation": "(-24.0783, -72.5997)"
    },
    {
      "name": "Trinh",
      "id": "10206",
      "recclass": "LL5",
      "mass (g)": "1464",
      "reclat": "-84.3567",
      "reclong": "-6.7211",
      "GeoLocation": "(-84.3567, -6.7211)"
    },
    {
      "name": "Willie",
      "id": "10207",
      "recclass": "LL3-6",
      "mass (g)": "4381",
      "reclat": "-57.7218",
      "reclong": "35.1710",
      "GeoLocation": "(-57.7218, 35.1710)"
    },
    {
      "name": "Jason",
      "id": "10208",
      "recclass": "CI1",
      "mass (g)": "4649",
      "reclat": "20.0775",
      "reclong": "-16.6937",
      "GeoLocation": "(20.0775, -16.6937)"
    },
    {
      "name": "Marilyn",
      "id": "10209",
      "recclass": "EH4",
      "mass (g)": "2051",
      "reclat": "-65.1754",
      "reclong": "-64.0666",
      "GeoLocation": "(-65.1754, -64.0666)"
    },
    {
      "name": "Lawrence",
      "id": "10210",
      "recclass": "H5",
      "mass (g)": "8367",
      "reclat": "61.7371",
      "reclong": "-49.2439",
      "GeoLocation": "(61.7371, -49.2439)"
    },
    {
      "name": "Rosalyn",
      "id": "10211",
      "recclass": "EH4",
      "mass (g)": "7147",
      "reclat": "49.0616",
      "reclong": "23.0492",
      "GeoLocation": "(49.0616, 23.0492)"
    },
    {
      "name": "Marcus",
      "id": "10212",
      "recclass": "EH4",
      "mass (g)": "4070",
      "reclat": "75.6244",
      "reclong": "-82.8783",
      "GeoLocation": "(75.6244, -82.8783)"
    },
    {
      "name": "Deborah",
      "id": "10213",
      "recclass": "LL5",
      "mass (g)": "6848",
      "reclat": "68.1142",
      "reclong": "-65.0634",
      "GeoLocation": "(68.1142, -65.0634)"
    },
    {
      "name": "Daniel",
      "id": "10214",
      "recclass": "CI1",
      "mass (g)": "8861",
      "reclat": "-42.7851",
      "reclong": "-71.8068",
      "GeoLocation": "(-42.7851, -71.8068)"
    },
    {
      "name": "Heather",
      "id": "10215",
      "recclass": "L5",
      "mass (g)": "6563",
      "reclat": "53.6919",
      "reclong": "-31.5961",
      "GeoLocation": "(53.6919, -31.5961)"
    },
    {
      "name": "Kayla",
      "id": "10216",
      "recclass": "LL3-6",
      "mass (g)": "933",
      "reclat": "41.2960",
      "reclong": "-26.0494",
      "GeoLocation": "(41.2960, -26.0494)"
    },
    {
      "name": "Jesse",
      "id": "10217",
      "recclass": "L5",
      "mass (g)": "2071",
      "reclat": "-45.0024",
      "reclong": "-58.7336",
      "GeoLocation": "(-45.0024, -58.7336)"
    },
    {
      "name": "Michelle",
      "id": "10218",
      "recclass": "H5",
      "mass (g)": "7142",
      "reclat": "-49.4879",
      "reclong": "85.4112",
      "GeoLocation": "(-49.4879, 85.4112)"
    },
    {
      "name": "Kathy",
      "id": "10219",
      "recclass": "CI1",
      "mass (g)": "6654",
      "reclat": "19.5879",
      "reclong": "-41.4758",
      "GeoLocation": "(19.5879, -41.4758)"
    },
    {
      "name": "Rita",
      "id": "10220",
      "recclass": "H6",
      "mass (g)": "4164",
      "reclat": "9.9229",
      "reclong": "46.2282",
      "GeoLocation": "(9.9229, 46.2282)"
    },
    {
      "name": "David",
      "id": "10221",
      "recclass": "H4",
      "mass (g)": "1792",
      "reclat": "56.5492",
      "reclong": "-29.3171",
      "GeoLocation": "(56.5492, -29.3171)"
    },
    {
      "name": "Julia",
      "id": "10222",
      "recclass": "H5",
      "mass (g)": "4428",
      "reclat": "84.8000",
      "reclong": "14.6012",
      "GeoLocation": "(84.8000, 14.6012)"
    },
    {
      "name": "Nancy",
      "id": "10223",
      "recclass": "EH4",
      "mass (g)": "6234",
      "reclat": "-24.6257",
      "reclong": "-44.6563",
      "GeoLocation": "(-24.6257, -44.6563)"
    },
    {
      "name": "Shane",
      "id": "10224",
      "recclass": "H6",
      "mass (g)": "7842",
      "reclat": "81.5453",
      "reclong": "72.2221",
      "GeoLocation": "(81.5453, 72.2221)"
    },
    {
      "name": "Wendy",
      "id": "10225",
      "recclass": "H6",
      "mass (g)": "2453",
      "reclat": "51.3589",
      "reclong": "-73.9690",
      "GeoLocation": "(51.3589, -73.9690)"
    },
    {
      "name": "Ruth",
      "id": "10226",
      "recclass": "H6",
      "mass (g)": "2323",
      "reclat": "63.2660",
      "reclong": "-83.6128",
      "GeoLocation": "(63.2660, -83.6128)"
    },
    {
      "name": "James",
      "id": "10227",
      "recclass": "H4",
      "mass (g)": "6097",
      "reclat": "65.0449",
      "reclong": "-68.6313",
      "GeoLocation": "(65.0449, -68.6313)"
    },
    {
      "name": "Edwin",
      "id": "10228",
      "recclass": "EH4",
      "mass (g)": "1234",
      "reclat": "63.7791",
      "reclong": "-34.2927",
      "GeoLocation": "(63.7791, -34.2927)"
    },
    {
      "name": "Rhonda",
      "id": "10229",
      "recclass": "H4",
      "mass (g)": "7380",
      "reclat": "41.6240",
      "reclong": "87.8566",
      "GeoLocation": "(41.6240, 87.8566)"
    },
    {
      "name": "Gearldine",
      "id": "10230",
      "recclass": "EH4",
      "mass (g)": "4829",
      "reclat": "64.9084",
      "reclong": "-81.3408",
      "GeoLocation": "(64.9084, -81.3408)"
    },
    {
      "name": "Jeffrey",
      "id": "10231",
      "recclass": "CI1",
      "mass (g)": "7110",
      "reclat": "-77.9600",
      "reclong": "-66.0166",
      "GeoLocation": "(-77.9600, -66.0166)"
    },
    {
      "name": "Ethel",
      "id": "10232",
      "recclass": "L6",
      "mass (g)": "1229",
      "reclat": "54.3929",
      "reclong": "-55.3516",
      "GeoLocation": "(54.3929, -55.3516)"
    },
    {
      "name": "Bo",
      "id": "10233",
      "recclass": "H4",
      "mass (g)": "9292",
      "reclat": "64.4177",
      "reclong": "-39.6520",
      "GeoLocation": "(64.4177, -39.6520)"
    },
    {
      "name": "Aaron",
      "id": "10234",
      "recclass": "L5",
      "mass (g)": "8541",
      "reclat": "-37.5478",
      "reclong": "-2.8258",
      "GeoLocation": "(-37.5478, -2.8258)"
    },
    {
      "name": "Gloria",
      "id": "10235",
      "recclass": "LL5",
      "mass (g)": "4113",
      "reclat": "-0.1350",
      "reclong": "32.6526",
      "GeoLocation": "(-0.1350, 32.6526)"
    },
    {
      "name": "Albert",
      "id": "10236",
      "recclass": "H6",
      "mass (g)": "746",
      "reclat": "-59.5086",
      "reclong": "81.4440",
      "GeoLocation": "(-59.5086, 81.4440)"
    },
    {
      "name": "Annie",
      "id": "10237",
      "recclass": "H6",
      "mass (g)": "1808",
      "reclat": "-41.4885",
      "reclong": "-87.2596",
      "GeoLocation": "(-41.4885, -87.2596)"
    },
    {
      "name": "Michael",
      "id": "10238",
      "recclass": "L5",
      "mass (g)": "7111",
      "reclat": "69.9900",
      "reclong": "22.7104",
      "GeoLocation": "(69.9900, 22.7104)"
    },
    {
      "name": "Michael",
      "id": "10239",
      "recclass": "LL5",
      "mass (g)": "6346",
      "reclat": "35.5240",
      "reclong": "63.9478",
      "GeoLocation": "(35.5240, 63.9478)"
    },
    {
      "name": "Sherry",
      "id": "10240",
      "recclass": "L6",
      "mass (g)": "4266",
      "reclat": "86.1758",
      "reclong": "45.0987",
      "GeoLocation": "(86.1758, 45.0987)"
    },
    {
      "name": "Christine",
      "id": "10241",
      "recclass": "H5",
      "mass (g)": "91",
      "reclat": "-23.8261",
      "reclong": "-34.3513",
      "GeoLocation": "(-23.8261, -34.3513)"
    },
    {
      "name": "Irene",
      "id": "10242",
      "recclass": "H4",
      "mass (g)": "523",
      "reclat": "63.6351",
      "reclong": "70.1761",
      "GeoLocation": "(63.6351, 70.1761)"
    },
    {
      "name": "Jessica",
      "id": "10243",
      "recclass": "H4",
      "mass (g)": "9625",
      "reclat": "-88.0465",
      "reclong": "85.4250",
      "GeoLocation": "(-88.0465, 85.4250)"
    },
    {
      "name": "Bob",
      "id": "10244",
      "recclass": "CV3",
      "mass (g)": "2549",
      "reclat": "21.0480",
      "reclong": "14.2567",
      "GeoLocation": "(21.0480, 14.2567)"
    },
    {
      "name": "Steven",
      "id": "10245",
      "recclass": "LL5",
      "mass (g)": "4258",
      "reclat": "8.0817",
      "reclong": "79.2811",
      "GeoLocation": "(8.0817, 79.2811)"
    },
    {
      "name": "Joseph",
      "id": "10246",
      "recclass": "L5",
      "mass (g)": "5591",
      "reclat": "-59.6935",
      "reclong": "-43.3125",
      "GeoLocation": "(-59.6935, -43.3125)"
    },
    {
      "name": "Dustin",
      "id": "10247",
      "recclass": "H6",
      "mass (g)": "3846",
      "reclat": "-33.2290",
      "reclong": "81.3118",
      "GeoLocation": "(-33.2290, 81.3118)"
    },
    {
      "name": "Keith",
      "id": "10248",
      "recclass": "CI1",
      "mass (g)": "4747",
      "reclat": "20.4415",
      "reclong": "-27.1940",
      "GeoLocation": "(20.4415, -27.1940)"
    },
    {
      "name": "Bill",
      "id": "10249",
      "recclass": "CR2-an",
      "mass (g)": "2158",
      "reclat": "-40.7920",
      "reclong": "80.5822",
      "GeoLocation": "(-40.7920, 80.5822)"
    },
    {
      "name": "Julia",
      "id": "10250",
      "recclass": "L5",
      "mass (g)": "2204",
      "reclat": "41.8311",
      "reclong": "-65.7171",
      "GeoLocation": "(41.8311, -65.7171)"
    },
    {
      "name": "Michael",
      "id": "10251",
      "recclass": "L6",
      "mass (g)": "7314",
      "reclat": "-0.6567",
      "reclong": "45.3839",
      "GeoLocation": "(-0.6567, 45.3839)"
    },
    {
      "name": "Karen",
      "id": "10252",
      "recclass": "H6",
      "mass (g)": "1295",
      "reclat": "-59.6086",
      "reclong": "21.0030",
      "GeoLocation": "(-59.6086, 21.0030)"
    },
    {
      "name": "Tony",
      "id": "10253",
      "recclass": "H6",
      "mass (g)": "1850",
      "reclat": "44.3286",
      "reclong": "-68.7897",
      "GeoLocation": "(44.3286, -68.7897)"
    },
    {
      "name": "Anthony",
      "id": "10254",
      "recclass": "CV3",
      "mass (g)": "1217",
      "reclat": "83.8254",
      "reclong": "58.7856",
      "GeoLocation": "(83.8254, 58.7856)"
    },
    {
      "name": "Beverly",
      "id": "10255",
      "recclass": "LL5",
      "mass (g)": "7408",
      "reclat": "47.8644",
      "reclong": "64.5041",
      "GeoLocation": "(47.8644, 64.5041)"
    },
    {
      "name": "Todd",
      "id": "10256",
      "recclass": "LL5",
      "mass (g)": "5811",
      "reclat": "-43.3209",
      "reclong": "-45.2145",
      "GeoLocation": "(-43.3209, -45.2145)"
    },
    {
      "name": "Dave",
      "id": "10257",
      "recclass": "L5",
      "mass (g)": "5577",
      "reclat": "-11.2443",
      "reclong": "-2.8751",
      "GeoLocation": "(-11.2443, -2.8751)"
    },
    {
      "name": "Mary",
      "id": "10258",
      "recclass": "H6",
      "mass (g)": "2954",
      "reclat": "49.7131",
      "reclong": "-44.1096",
      "GeoLocation": "(49.7131, -44.1096)"
    },
    {
      "name": "Dorothy",
      "id": "10259",
      "recclass": "H6",
      "mass (g)": "9539",
      "reclat": "26.3462",
      "reclong": "-73.4656",
      "GeoLocation": "(26.3462, -73.4656)"
    },
    {
      "name": "Cleveland",
      "id": "10260",
      "recclass": "L5",
      "mass (g)": "2015",
      "reclat": "-68.3249",
      "reclong": "18.5087",
      "GeoLocation": "(-68.3249, 18.5087)"
    },
    {
      "name": "Franklin",
      "id": "10261",
      "recclass": "H6",
      "mass (g)": "3763",
      "reclat": "-45.1640",
      "reclong": "-31.4661",
      "GeoLocation": "(-45.1640, -31.4661)"
    },
    {
      "name": "Concepcion",
      "id": "10262",
      "recclass": "H4",
      "mass (g)": "2419",
      "reclat": "-82.6519",
      "reclong": "26.3623",
      "GeoLocation": "(-82.6519, 26.3623)"
    },
    {
      "name": "Michael",
      "id": "10263",
      "recclass": "L5",
      "mass (g)": "7650",
      "reclat": "-32.7119",
      "reclong": "-44.4996",
      "GeoLocation": "(-32.7119, -44.4996)"
    },
    {
      "name": "Kay",
      "id": "10264",
      "recclass": "LL3-6",
      "mass (g)": "2326",
      "reclat": "-77.8308",
      "reclong": "82.1998",
      "GeoLocation": "(-77.8308, 82.1998)"
    },
    {
      "name": "Judy",
      "id": "10265",
      "recclass": "LL5",
      "mass (g)": "9640",
      "reclat": "-24.5061",
      "reclong": "-20.0704",
      "GeoLocation": "(-24.5061, -20.0704)"
    },
    {
      "name": "Keith",
      "id": "10266",
      "recclass": "LL5",
      "mass (g)": "1983",
      "reclat": "-26.1973",
      "reclong": "53.2871",
      "GeoLocation": "(-26.1973, 53.2871)"
    },
    {
      "name": "David",
      "id": "10267",
      "recclass": "L5",
      "mass (g)": "408",
      "reclat": "66.4240",
      "reclong": "13.5134",
      "GeoLocation": "(66.4240, 13.5134)"
    },
    {
      "name": "Andrea",
      "id": "10268",
      "recclass": "L6",
      "mass (g)": "1682",
      "reclat": "51.2486",
      "reclong": "-72.9165",
      "GeoLocation": "(51.2486, -72.9165)"
    },
    {
      "name": "Krystyna",
      "id": "10269",
      "recclass": "CR2-an",
      "mass (g)": "5303",
      "reclat": "83.7896",
      "reclong": "76.8485",
      "GeoLocation": "(83.7896, 76.8485)"
    },
    {
      "name": "Gregorio",
      "id": "10270",
      "recclass": "CV3",
      "mass (g)": "4330",
      "reclat": "61.0332",
      "reclong": "-45.4310",
      "GeoLocation": "(61.0332, -45.4310)"
    },
    {
      "name": "George",
      "id": "10271",
      "recclass": "CI1",
      "mass (g)": "1783",
      "reclat": "7.4716",
      "reclong": "23.7368",
      "GeoLocation": "(7.4716, 23.7368)"
    },
    {
      "name": "Elizabeth",
      "id": "10272",
      "recclass": "LL5",
      "mass (g)": "1475",
      "reclat": "8.2327",
      "reclong": "8.2381",
      "GeoLocation": "(8.2327, 8.2381)"
    },
    {
      "name": "Glenn",
      "id": "10273",
      "recclass": "CR2-an",
      "mass (g)": "8652",
      "reclat": "-81.9038",
      "reclong": "14.1611",
      "GeoLocation": "(-81.9038, 14.1611)"
    },
    {
      "name": "Mildred",
      "id": "10274",
      "recclass": "LL5",
      "mass (g)": "4530",
      "reclat": "9.5485",
      "reclong": "-75.0730",
      "GeoLocation": "(9.5485, -75.0730)"
    },
    {
      "name": "Vasiliki",
      "id": "10275",
      "recclass": "L5",
      "mass (g)": "6244",
      "reclat": "-25.3606",
      "reclong": "-31.6027",
      "GeoLocation": "(-25.3606, -31.6027)"
    },
    {
      "name": "Jean",
      "id": "10276",
      "recclass": "LL5",
      "mass (g)": "912",
      "reclat": "-41.3710",
      "reclong": "-67.1293",
      "GeoLocation": "(-41.3710, -67.1293)"
    },
    {
      "name": "Leah",
      "id": "10277",
      "recclass": "L5",
      "mass (g)": "4306",
      "reclat": "14.7228",
      "reclong": "-18.6471",
      "GeoLocation": "(14.7228, -18.6471)"
    },
    {
      "name": "Stacy",
      "id": "10278",
      "recclass": "L5",
      "mass (g)": "5810",
      "reclat": "-37.5100",
      "reclong": "32.2823",
      "GeoLocation": "(-37.5100, 32.2823)"
    },
    {
      "name": "Juan",
      "id": "10279",
      "recclass": "H5",
      "mass (g)": "1949",
      "reclat": "11.4302",
      "reclong": "8.9024",
      "GeoLocation": "(11.4302, 8.9024)"
    },
    {
      "name": "Andrea",
      "id": "10280",
      "recclass": "H5",
      "mass (g)": "8609",
      "reclat": "14.9460",
      "reclong": "-15.7281",
      "GeoLocation": "(14.9460, -15.7281)"
    },
    {
      "name": "Christine",
      "id": "10281",
      "recclass": "H6",
      "mass (g)": "6080",
      "reclat": "27.8482",
      "reclong": "-14.0151",
      "GeoLocation": "(27.8482, -14.0151)"
    },
    {
      "name": "Cathy",
      "id": "10282",
      "recclass": "L5",
      "mass (g)": "4821",
      "reclat": "4.6435",
      "reclong": "-45.9889",
      "GeoLocation": "(4.6435, -45.9889)"
    },
    {
      "name": "Floyd",
      "id": "10283",
      "recclass": "H5",
      "mass (g)": "5206",
      "reclat": "1.0461",
      "reclong": "-21.6135",
      "GeoLocation": "(1.0461, -21.6135)"
    },
    {
      "name": "John",
      "id": "10284",
      "recclass": "H4",
      "mass (g)": "4725",
      "reclat": "-61.4692",
      "reclong": "-63.9141",
      "GeoLocation": "(-61.4692, -63.9141)"
    },
    {
      "name": "Shawn",
      "id": "10285",
      "recclass": "L6",
      "mass (g)": "3708",
      "reclat": "55.6215",
      "reclong": "-5.1274",
      "GeoLocation": "(55.6215, -5.1274)"
    },
    {
      "name": "Susan",
      "id": "10286",
      "recclass": "CR2-an",
      "mass (g)": "8299",
      "reclat": "-8.1030",
      "reclong": "-18.9423",
      "GeoLocation": "(-8.1030, -18.9423)"
    },
    {
      "name": "Tracy",
      "id": "10287",
      "recclass": "LL3-6",
      "mass (g)": "8044",
      "reclat": "0.4275",
      "reclong": "-61.2425",
      "GeoLocation": "(0.4275, -61.2425)"
    },
    {
      "name": "Amy",
      "id": "10288",
      "recclass": "H5",
      "mass (g)": "4093",
      "reclat": "-83.5050",
      "reclong": "-76.8306",
      "GeoLocation": "(-83.5050, -76.8306)"
    },
    {
      "name": "Beaulah",
      "id": "10289",
      "recclass": "LL5",
      "mass (g)": "6140",
      "reclat": "12.0404",
      "reclong": "63.6188",
      "GeoLocation": "(12.0404, 63.6188)"
    },
    {
      "name": "John",
      "id": "10290",
      "recclass": "CI1",
      "mass (g)": "8497",
      "reclat": "2.0107",
      "reclong": "63.5451",
      "GeoLocation": "(2.0107, 63.5451)"
    },
    {
      "name": "Ronnie",
      "id": "10291",
      "recclass": "L5",
      "mass (g)": "2167",
      "reclat": "-73.1466",
      "reclong": "73.5657",
      "GeoLocation": "(-73.1466, 73.5657)"
    },
    {
      "name": "Zena",
      "id": "10292",
      "recclass": "CI1",
      "mass (g)": "6870",
      "reclat": "69.4377",
      "reclong": "-17.1787",
      "GeoLocation": "(69.4377, -17.1787)"
    },
    {
      "name": "Linda",
      "id": "10293",
      "recclass": "CR2-an",
      "mass (g)": "4764",
      "reclat": "-20.2853",
      "reclong": "71.0405",
      "GeoLocation": "(-20.2853, 71.0405)"
    },
    {
      "name": "Sarah",
      "id": "10294",
      "recclass": "L5",
      "mass (g)": "9003",
      "reclat": "-10.4099",
      "reclong": "-15.0310",
      "GeoLocation": "(-10.4099, -15.0310)"
    },
    {
      "name": "Mary",
      "id": "10295",
      "recclass": "EH4",
      "mass (g)": "7533",
      "reclat": "-15.7062",
      "reclong": "-19.2370",
      "GeoLocation": "(-15.7062, -19.2370)"
    },
    {
      "name": "Jo",
      "id": "10296",
      "recclass": "EH4",
      "mass (g)": "2554",
      "reclat": "24.4095",
      "reclong": "-15.7901",
      "GeoLocation": "(24.4095, -15.7901)"
    },
    {
      "name": "Thomas",
      "id": "10297",
      "recclass": "H6",
      "mass (g)": "8670",
      "reclat": "-60.7340",
      "reclong": "54.3187",
      "GeoLocation": "(-60.7340, 54.3187)"
    },
    {
      "name": "Agnes",
      "id": "10298",
      "recclass": "H6",
      "mass (g)": "801",
      "reclat": "-61.5820",
      "reclong": "-10.3998",
      "GeoLocation": "(-61.5820, -10.3998)"
    },
    {
      "name": "Jennifer",
      "id": "10299",
      "recclass": "L5",
      "mass (g)": "539",
      "reclat": "-84.0579",
      "reclong": "69.9994",
      "GeoLocation": "(-84.0579, 69.9994)"
    },
    {
      "name": "Christina",
      "id": "10300",
      "recclass": "H5",
      "mass (g)": "4291",
      "reclat": "-38.1533",
      "reclong": "-46.7127",
      "GeoLocation": "(-38.1533, -46.7127)"
    }
  ]
}